my_happy_pandas-1.1.10.dist-info/WHEEL
my_happy_pandas-1.1.10.dist-info/entry_points.txt
my_happy_pandas-1.1.10.dist-info/LICENSE
my_happy_pandas-1.1.10.dist-info/RECORD
my_happy_pandas-1.1.10.dist-info/METADATA
my_happy_pandas-1.1.10.dist-info/top_level.txt
my_happy_pandas/_testing.py
my_happy_pandas/testing.py
my_happy_pandas/conftest.py
my_happy_pandas/_version.py
my_happy_pandas/_typing.py
my_happy_pandas/__init__.py
my_happy_pandas/errors/__init__.py
my_happy_pandas/tseries/holiday.py
my_happy_pandas/tseries/api.py
my_happy_pandas/tseries/frequencies.py
my_happy_pandas/tseries/__init__.py
my_happy_pandas/tseries/offsets.py
my_happy_pandas/plotting/_core.py
my_happy_pandas/plotting/__init__.py
my_happy_pandas/plotting/_misc.py
my_happy_pandas/plotting/_matplotlib/hist.py
my_happy_pandas/plotting/_matplotlib/misc.py
my_happy_pandas/plotting/_matplotlib/tools.py
my_happy_pandas/plotting/_matplotlib/converter.py
my_happy_pandas/plotting/_matplotlib/compat.py
my_happy_pandas/plotting/_matplotlib/__init__.py
my_happy_pandas/plotting/_matplotlib/style.py
my_happy_pandas/plotting/_matplotlib/core.py
my_happy_pandas/plotting/_matplotlib/timeseries.py
my_happy_pandas/plotting/_matplotlib/boxplot.py
my_happy_pandas/compat/pickle_compat.py
my_happy_pandas/compat/__init__.py
my_happy_pandas/compat/_optional.py
my_happy_pandas/compat/chainmap.py
my_happy_pandas/compat/numpy/__init__.py
my_happy_pandas/compat/numpy/function.py
my_happy_pandas/_libs/algos.cpython-37m-x86_64-linux-gnu.so
my_happy_pandas/_libs/testing.cpython-37m-x86_64-linux-gnu.so
my_happy_pandas/_libs/interval.cpython-37m-x86_64-linux-gnu.so
my_happy_pandas/_libs/lib.cpython-37m-x86_64-linux-gnu.so
my_happy_pandas/_libs/join.cpython-37m-x86_64-linux-gnu.so
my_happy_pandas/_libs/reshape.cpython-37m-x86_64-linux-gnu.so
my_happy_pandas/_libs/writers.cpython-37m-x86_64-linux-gnu.so
my_happy_pandas/_libs/hashtable.cpython-37m-x86_64-linux-gnu.so
my_happy_pandas/_libs/json.cpython-37m-x86_64-linux-gnu.so
my_happy_pandas/_libs/ops.cpython-37m-x86_64-linux-gnu.so
my_happy_pandas/_libs/internals.cpython-37m-x86_64-linux-gnu.so
my_happy_pandas/_libs/__init__.py
my_happy_pandas/_libs/ops_dispatch.cpython-37m-x86_64-linux-gnu.so
